Workbook
Name aporte: APP!$D$17
Name patrimonio: APP!$D$20
Name qtd_anos: APP!$D$18
Name rendimento_carteira: APP!$D$13
Name salario: APP!$D$12
Name sugestao_investimento: APP!$D$14
Name taxa_mensal: APP!$D$19

Sheet Simulador
B2: SIMULADOR DE INVESTIMENTOS EM FUNDOS IMOBILIÁRIOS
B3: Ferramenta educacional para simular patrimônio, aportes e dividendos ao longo do tempo.
B5: PARÂMETROS DA SIMULAÇÃO | E5: Total investido | G5: Patrimônio final | I5: Dividendos mensais estimados | K5: Cotas estimadas | M5: Rendimentos acumulados
B6: Investimento inicial | C6: 1000 | E6: =IFERROR(C6+(C7*C8),0) -> 31000 | G6: =IFERROR(INDEX($F$19:$F$138,$C$8),0) -> 319.29698 | I6: =IFERROR(INDEX($H$19:$H$138,$C$8),0) -> 9231.4198 | K6: =IFERROR(INDEX($I$19:$I$138,$C$8),0) -> 321.85136 | M6: =IFERROR(INDEX($G$19:$G$138,$C$8),0) -> 40231.42
B7: Aporte mensal | C7: 500
B8: Prazo (meses) | C8: 60
B9: Taxa de rendimento mensal | C9: 0.008
B10: Valor da cota do FII | C10: 100
B11: Dividend yield mensal estimado | C11: 0.008
B12: Observação | C12: Altere apenas as células amarelas.
B14: COMO UTILIZAR
B15: 1. Informe o investimento inicial e o aporte mensal. 2. Informe o prazo em meses. 3. Informe a taxa mensal estimada. 4. Informe o valor da cota e o dividend yield. 5. Consulte os indicadores e gráficos.
B16: PREMISSAS: o aporte é considerado no início de cada mês; o rendimento mensal é aplicado sobre o patrimônio após o aporte; dividendos são estimados pelo patrimônio final do mês × DY mensal. A simulação é educacional e não representa garantia de rentabilidade.
B18: Mês | C18: Aporte mensal | D18: Total aportado acumulado | E18: Patrimônio inicial | F18: Rendimento do mês | G18: Patrimônio final | H18: Rendimentos acumulados | I18: Dividendos estimados | J18: Cotas acumuladas
B19: =IF(ROW()-18<=$C$8,ROW()-18,"") -> 1 | C19: =IF(B19="","",$C$7) -> 500 | D19: =IF(B19="","",$C$6+C19*B19) -> 1500 | E19: =IF(B19="","",IF(B19=1,$C$6,E18*0+G18)) -> 1000 | F19: =IF(B19="","",IFERROR((E19+C19)*$C$9,0)) -> 12 | G19: =IF(B19="","",E19+C19+F19) -> 1512 | H19: =IF(B19="","",G19-D19) -> 12 | I19: =IF(B19="","",IFERROR(G19*$C$11,0)) -> 12.096 | J19: =IF(B19="","",IFERROR(G19/$C$10,0)) -> 15.12
B20: =IF(ROW()-18<=$C$8,ROW()-18,"") -> 2 | C20: =IF(B20="","",$C$7) -> 500 | D20: =IF(B20="","",$C$6+C20*B20) -> 2000 | E20: =IF(B20="","",IF(B20=1,$C$6,E19*0+G19)) -> 1512 | F20: =IF(B20="","",IFERROR((E20+C20)*$C$9,0)) -> 16.096 | G20: =IF(B20="","",E20+C20+F20) -> 2028.096 | H20: =IF(B20="","",G20-D20) -> 28.096 | I20: =IF(B20="","",IFERROR(G20*$C$11,0)) -> 16.224768 | J20: =IF(B20="","",IFERROR(G20/$C$10,0)) -> 20.28096
B21: =IF(ROW()-18<=$C$8,ROW()-18,"") -> 3 | C21: =IF(B21="","",$C$7) -> 500 | D21: =IF(B21="","",$C$6+C21*B21) -> 2500 | E21: =IF(B21="","",IF(B21=1,$C$6,E20*0+G20)) -> 2028.096 | F21: =IF(B21="","",IFERROR((E21+C21)*$C$9,0)) -> 20.224768 | G21: =IF(B21="","",E21+C21+F21) -> 2548.3208 | H21: =IF(B21="","",G21-D21) -> 48.320768 | I21: =IF(B21="","",IFERROR(G21*$C$11,0)) -> 20.386566 | J21: =IF(B21="","",IFERROR(G21/$C$10,0)) -> 25.483208
B22: =IF(ROW()-18<=$C$8,ROW()-18,"") -> 4 | C22: =IF(B22="","",$C$7) -> 500 | D22: =IF(B22="","",$C$6+C22*B22) -> 3000 | E22: =IF(B22="","",IF(B22=1,$C$6,E21*0+G21)) -> 2548.3208 | F22: =IF(B22="","",IFERROR((E22+C22)*$C$9,0)) -> 24.386566 | G22: =IF(B22="","",E22+C22+F22) -> 3072.7073 | H22: =IF(B22="","",G22-D22) -> 72.707334 | I22: =IF(B22="","",IFERROR(G22*$C$11,0)) -> 24.581659 | J22: =IF(B22="","",IFERROR(G22/$C$10,0)) -> 30.727073
B23: =IF(ROW()-18<=$C$8,ROW()-18,"") -> 5 | C23: =IF(B23="","",$C$7) -> 500 | D23: =IF(B23="","",$C$6+C23*B23) -> 3500 | E23: =IF(B23="","",IF(B23=1,$C$6,E22*0+G22)) -> 3072.7073 | F23: =IF(B23="","",IFERROR((E23+C23)*$C$9,0)) -> 28.581659 | G23: =IF(B23="","",E23+C23+F23) -> 3601.289 | H23: =IF(B23="","",G23-D23) -> 101.28899 | I23: =IF(B23="","",IFERROR(G23*$C$11,0)) -> 28.810312 | J23: =IF(B23="","",IFERROR(G23/$C$10,0)) -> 36.01289
B24: =IF(ROW()-18<=$C$8,ROW()-18,"") -> 6 | C24: =IF(B24="","",$C$7) -> 500 | D24: =IF(B24="","",$C$6+C24*B24) -> 4000 | E24: =IF(B24="","",IF(B24=1,$C$6,E23*0+G23)) -> 3601.289 | F24: =IF(B24="","",IFERROR((E24+C24)*$C$9,0)) -> 32.810312 | G24: =IF(B24="","",E24+C24+F24) -> 4134.0993 | H24: =IF(B24="","",G24-D24) -> 134.0993 | I24: =IF(B24="","",IFERROR(G24*$C$11,0)) -> 33.072794 | J24: =IF(B24="","",IFERROR(G24/$C$10,0)) -> 41.340993
B25: =IF(ROW()-18<=$C$8,ROW()-18,"") -> 7 | C25: =IF(B25="","",$C$7) -> 500 | D25: =IF(B25="","",$C$6+C25*B25) -> 4500 | E25: =IF(B25="","",IF(B25=1,$C$6,E24*0+G24)) -> 4134.0993 | F25: =IF(B25="","",IFERROR((E25+C25)*$C$9,0)) -> 37.072794 | G25: =IF(B25="","",E25+C25+F25) -> 4671.1721 | H25: =IF(B25="","",G25-D25) -> 171.1721 | I25: =IF(B25="","",IFERROR(G25*$C$11,0)) -> 37.369377 | J25: =IF(B25="","",IFERROR(G25/$C$10,0)) -> 46.711721
B26: =IF(ROW()-18<=$C$8,ROW()-18,"") -> 8 | C26: =IF(B26="","",$C$7) -> 500 | D26: =IF(B26="","",$C$6+C26*B26) -> 5000 | E26: =IF(B26="","",IF(B26=1,$C$6,E25*0+G25)) -> 4671.1721 | F26: =IF(B26="","",IFERROR((E26+C26)*$C$9,0)) -> 41.369377 | G26: =IF(B26="","",E26+C26+F26) -> 5212.5415 | H26: =IF(B26="","",G26-D26) -> 212.54148 | I26: =IF(B26="","",IFERROR(G26*$C$11,0)) -> 41.700332 | J26: =IF(B26="","",IFERROR(G26/$C$10,0)) -> 52.125415
B27: =IF(ROW()-18<=$C$8,ROW()-18,"") -> 9 | C27: =IF(B27="","",$C$7) -> 500 | D27: =IF(B27="","",$C$6+C27*B27) -> 5500 | E27: =IF(B27="","",IF(B27=1,$C$6,E26*0+G26)) -> 5212.5415 | F27: =IF(B27="","",IFERROR((E27+C27)*$C$9,0)) -> 45.700332 | G27: =IF(B27="","",E27+C27+F27) -> 5758.2418 | H27: =IF(B27="","",G27-D27) -> 258.24181 | I27: =IF(B27="","",IFERROR(G27*$C$11,0)) -> 46.065934 | J27: =IF(B27="","",IFERROR(G27/$C$10,0)) -> 57.582418
B28: =IF(ROW()-18<=$C$8,ROW()-18,"") -> 10 | C28: =IF(B28="","",$C$7) -> 500 | D28: =IF(B28="","",$C$6+C28*B28) -> 6000 | E28: =IF(B28="","",IF(B28=1,$C$6,E27*0+G27)) -> 5758.2418 | F28: =IF(B28="","",IFERROR((E28+C28)*$C$9,0)) -> 50.065934 | G28: =IF(B28="","",E28+C28+F28) -> 6308.3077 | H28: =IF(B28="","",G28-D28) -> 308.30774 | I28: =IF(B28="","",IFERROR(G28*$C$11,0)) -> 50.466462 | J28: =IF(B28="","",IFERROR(G28/$C$10,0)) -> 63.083077
B29: =IF(ROW()-18<=$C$8,ROW()-18,"") -> 11 | C29: =IF(B29="","",$C$7) -> 500 | D29: =IF(B29="","",$C$6+C29*B29) -> 6500 | E29: =IF(B29="","",IF(B29=1,$C$6,E28*0+G28)) -> 6308.3077 | F29: =IF(B29="","",IFERROR((E29+C29)*$C$9,0)) -> 54.466462 | G29: =IF(B29="","",E29+C29+F29) -> 6862.7742 | H29: =IF(B29="","",G29-D29) -> 362.7742 | I29: =IF(B29="","",IFERROR(G29*$C$11,0)) -> 54.902194 | J29: =IF(B29="","",IFERROR(G29/$C$10,0)) -> 68.627742
B30: =IF(ROW()-18<=$C$8,ROW()-18,"") -> 12 | C30: =IF(B30="","",$C$7) -> 500 | D30: =IF(B30="","",$C$6+C30*B30) -> 7000 | E30: =IF(B30="","",IF(B30=1,$C$6,E29*0+G29)) -> 6862.7742 | F30: =IF(B30="","",IFERROR((E30+C30)*$C$9,0)) -> 58.902194 | G30: =IF(B30="","",E30+C30+F30) -> 7421.6764 | H30: =IF(B30="","",G30-D30) -> 421.6764 | I30: =IF(B30="","",IFERROR(G30*$C$11,0)) -> 59.373411 | J30: =IF(B30="","",IFERROR(G30/$C$10,0)) -> 74.216764
... B138: =IF(ROW()-18<=$C$8,ROW()-18,"") | C138: =IF(B138="","",$C$7) | D138: =IF(B138="","",$C$6+C138*B138) | E138: =IF(B138="","",IF(B138=1,$C$6,E137*0+G137)) | F138: =IF(B138="","",IFERROR((E138+C138)*$C$9,0)) | G138: =IF(B138="","",E138+C138+F138) | H138: =IF(B138="","",G138-D138) | I138: =IF(B138="","",IFERROR(G138*$C$11,0)) | J138: =IF(B138="","",IFERROR(G138/$C$10,0))
B159: Uso educacional • Os resultados são estimativas matemáticas e não constituem recomendação de investimento.

Sheet APP
B11: CONFIGURAÇÕES
B12: Salário | D12: 2000
B13: Rendimento Carteira | D13: 0.006
B14: Sugestão de Investimento (30%) | D14: =D12*30% -> 600
B16: INVESTIMENTO MENSAL
B17: Quanto investir por mês ? | D17: 200
B18: Por Quantos Anos ? | D18: 5
B19: Taxa de Rendimento mensal ? | D19: 0.01079
B20: Patrimônio acumulado ? | D20: =FV(taxa_mensal,qtd_anos*12,aporte*-1) -> 16755.383
B21: Dividendos Mensais ? | D21: =patrimonio*rendimento_carteira -> 100.5323
B23: Cenários | D23: Dividendo
A24: 2 | B24: Quanto em 2 Anos ? | C24: =FV($D$19,$A24*12,$D$17*-1) -> 5445.5255 | D24: =C24*rendimento_carteira -> 32.673153
A25: 5 | B25: Quanto em 5 Anos ? | C25: =FV($D$19,$A25*12,$D$17*-1) -> 16755.383 | D25: =C25*rendimento_carteira -> 100.5323
A26: 10 | B26: Quanto em 10 Anos ? | C26: =FV($D$19,$A26*12,$D$17*-1) -> 48656.843 | D26: =C26*rendimento_carteira -> 291.94106
A27: 20 | B27: Quanto em 20 Anos ? | C27: =FV($D$19,$A27*12,$D$17*-1) -> 225039.68 | D27: =C27*rendimento_carteira -> 1350.2381
A28: 30 | B28: Quanto em 30 Anos ? | C28: =FV($D$19,$A28*12,$D$17*-1) -> 864433.93 | D28: =C28*rendimento_carteira -> 5186.6036
B32: PERFIL | C32: Moderado
B33: VALOR A SER INVESTIDO POR MÊS | C33: =aporte -> 200
B35: TIPO DE FII | C35: Percentual Sugerido | D35: Valores
B36: PAPEL | C36: =VLOOKUP($C$32&"-"&B36,Planilha2!$A:$D,4,FALSE) -> 0.32 | D36: =C36*$C$33 -> 64
B37: TIJOLO | C37: =VLOOKUP($C$32&"-"&B37,Planilha2!$A:$D,4,FALSE) -> 0.35 | D37: =C37*$C$33 -> 70
B38: HÍBRIDOS | C38: =VLOOKUP($C$32&"-"&B38,Planilha2!$A:$D,4,FALSE) -> 0.08 | D38: =C38*$C$33 -> 16
B39: FOFs | C39: =VLOOKUP($C$32&"-"&B39,Planilha2!$A:$D,4,FALSE) -> 0.05 | D39: =C39*$C$33 -> 10
B40: DESENVOLVIMENTO | C40: =VLOOKUP($C$32&"-"&B40,Planilha2!$A:$D,4,FALSE) -> 0.1 | D40: =C40*$C$33 -> 20
B41: HOTELARIAS | C41: =VLOOKUP($C$32&"-"&B41,Planilha2!$A:$D,4,FALSE) -> 0.1 | D41: =C41*$C$33 -> 20
D42: =SUM(D36:D41) -> 200

Sheet Planilha2
A2: CHAVE | B2: PERFIL | C2: TIPO DE FII | D2: %
A3: =B3&"-"&C3 -> Conservador-PAPEL | B3: Conservador | C3: PAPEL | D3: 0.3 | H3: %
A4: =B4&"-"&C4 -> Conservador-TIJOLO | B4: Conservador | C4: TIJOLO | D4: 0.5 | G4: Moderado-TIJOLO | H4: =VLOOKUP(G4,$A:$D,4,FALSE) -> 0.35
A5: =B5&"-"&C5 -> Conservador-HÍBRIDOS | B5: Conservador | C5: HÍBRIDOS | D5: 0.1
A6: =B6&"-"&C6 -> Conservador-FOFs | B6: Conservador | C6: FOFs | D6: 0.1
A7: =B7&"-"&C7 -> Conservador-DESENVOLVIMENTO | B7: Conservador | C7: DESENVOLVIMENTO | D7: 0
A8: =B8&"-"&C8 -> Conservador-HOTELARIAS | B8: Conservador | C8: HOTELARIAS | D8: 0
A9: =B9&"-"&C9 -> Moderado-PAPEL | B9: Moderado | C9: PAPEL | D9: 0.32
A10: =B10&"-"&C10 -> Moderado-TIJOLO | B10: Moderado | C10: TIJOLO | D10: 0.35
A11: =B11&"-"&C11 -> Moderado-HÍBRIDOS | B11: Moderado | C11: HÍBRIDOS | D11: 0.08
A12: =B12&"-"&C12 -> Moderado-FOFs | B12: Moderado | C12: FOFs | D12: 0.05
A13: =B13&"-"&C13 -> Moderado-DESENVOLVIMENTO | B13: Moderado | C13: DESENVOLVIMENTO | D13: 0.1
A14: =B14&"-"&C14 -> Moderado-HOTELARIAS | B14: Moderado | C14: HOTELARIAS | D14: 0.1
A15: =B15&"-"&C15 -> Agressivo-PAPEL | B15: Agressivo | C15: PAPEL | D15: 0.5
A16: =B16&"-"&C16 -> Agressivo-TIJOLO | B16: Agressivo | C16: TIJOLO | D16: 0.1
... A20: =B20&"-"&C20 -> Agressivo-HOTELARIAS | B20: Agressivo | C20: HOTELARIAS | D20: 0.1

Sheet Notas
A1: GUIA RÁPIDO DAS FÓRMULAS
A3: Total investido | B3: Investimento inicial + (aporte mensal × quantidade de meses).
A4: Patrimônio final | B4: Patrimônio inicial + aporte do mês + rendimento do mês.
A5: Rendimento mensal | B5: (Patrimônio inicial + aporte mensal) × taxa de rendimento mensal.
A6: Rendimentos acumulados | B6: Patrimônio final − total aportado acumulado.
A7: Dividendos estimados | B7: Patrimônio final × dividend yield mensal estimado.
A8: Cotas estimadas | B8: Patrimônio final ÷ valor da cota. É uma aproximação e não simula compras fracionadas, taxas ou variações de preço.
